PIL
_distutils_hack
absl
apiclient
astunparse
cachetools
certifi
cffi
charset_normalizer
clang
contourpy
cryptography
dateutil
distlib
filelock
flatbuffers
fontTools
gast
google_auth_oauthlib
googleapiclient
grpc
h5py
httplib2
idna
keras
kiwisolver
markdown
markupsafe
matplotlib
mis_modulos
mpl_toolkits
numpy
oauthlib
opt_einsum
packaging
pandas
pasta
pdfminer
pdfplumber
pip
pkg_resources
platformdirs
pyasn1
pyasn1_modules
pycparser
pyparsing
pytz
requests
requests_oauthlib
rsa
setuptools
tensorboard
tensorboard_data_server
tensorboard_plugin_wit
tensorflow
tensorflow_estimator
tensorflow_io_gcs_filesystem
termcolor
tomli
uritemplate
urllib3
virtualenv
wand
werkzeug
wheel
wrapt
