Metadata-Version: 2.1
Name: mis-modulos
Version: 0.1
Summary: Una descripción breve del paquete
Author: Luciano Delgado
Classifier: Programming Language :: Python :: 3
Classifier: License :: OSI Approved :: MIT License
Classifier: Operating System :: OS Independent
